sd_controls/__init__.py
sd_controls/sdsystem.py
sd_controls/sprites.py
sd_controls/streamdeck.py
sd_controls/virtualdeck.py
sd_controls/fonts/Roboto/.DS_Store
sd_controls/fonts/Roboto/LICENSE.txt
sd_controls/fonts/Roboto/Roboto-Regular.ttf
sd_controls/imgs/back_btn.jpeg
sd_controls/imgs/clear.jpeg
sd_controls/imgs/goat.jpeg
sd_controls-0.0.15.dist-info/LICENSE
sd_controls-0.0.15.dist-info/METADATA
sd_controls-0.0.15.dist-info/WHEEL
sd_controls-0.0.15.dist-info/top_level.txt
sd_controls-0.0.15.dist-info/RECORD
