Metadata-Version: 2.1
Name: sd_controls
Version: 0.0.15
Summary: A small and simple framework for streamdeck applications
Home-page: https://github.com/niklasr22/streamdeck-controls
Author-email: byrousset@gmail.com
License: MIT
Project-URL: Bug Tracker, https://github.com/niklasr22/streamdeck-controls/issues
Keywords: streamdeck
Classifier: Programming Language :: Python :: 3
Classifier: License :: OSI Approved :: MIT License
Classifier: Operating System :: OS Independent
Requires-Python: >=3.11
License-File: LICENSE
Requires-Dist: hid
Requires-Dist: Pillow
Requires-Dist: requests
